[{"name":"diamond.png","uploadEpochTime":1691785024950,"modifiedEpochTime":"","generatedEpochTime":"","height":932,"width":633,"og":{"height":932,"width":633}},{"name":"coin.png","uploadEpochTime":1691782737514,"modifiedEpochTime":"","generatedEpochTime":"","height":886,"width":884,"og":{"height":886,"width":884}},{"name":"scoobydoo_therapy_dave.jpg","uploadEpochTime":1691619775973,"modifiedEpochTime":"","generatedEpochTime":"","height":666,"width":500,"og":{"height":666,"width":500}},{"name":"startrek-trek.gif","uploadEpochTime":1691619739438,"modifiedEpochTime":"","generatedEpochTime":"","height":276,"width":350,"og":{"height":276,"width":350}},{"name":"hero.webp","uploadEpochTime":1687985834817,"modifiedEpochTime":"","generatedEpochTime":"","height":544,"width":1440,"og":{"height":544,"width":1440}},{"name":"group-photo7.jpg","uploadEpochTime":1687985753300,"modifiedEpochTime":"","generatedEpochTime":"","height":590,"width":1583,"og":{"height":590,"width":1583}},{"name":"1015-1600x800.jpg","uploadEpochTime":1687791306978,"modifiedEpochTime":"","generatedEpochTime":"","height":800,"width":1600,"og":{"height":800,"width":1600}},{"name":"206-200x200.jpg","uploadEpochTime":1687788052233,"modifiedEpochTime":"","generatedEpochTime":"","height":200,"width":200,"og":{"height":200,"width":200}},{"name":"853-200x200.jpg","uploadEpochTime":1687788052233,"modifiedEpochTime":"","generatedEpochTime":"","height":200,"width":200,"og":{"height":200,"width":200}},{"name":"825-200x200.jpg","uploadEpochTime":1687788052233,"modifiedEpochTime":"","generatedEpochTime":"","height":200,"width":200,"og":{"height":200,"width":200}},{"name":"539-200x200.jpg","uploadEpochTime":1687788052233,"modifiedEpochTime":"","generatedEpochTime":"","height":200,"width":200,"og":{"height":200,"width":200}}]
